django_aiml/__init__.py
django_aiml/__main__.py
django_aiml/py.typed
django_aiml-0.0.0.dist-info/entry_points.txt
django_aiml-0.0.0.dist-info/LICENSE.rst
django_aiml-0.0.0.dist-info/WHEEL
django_aiml-0.0.0.dist-info/METADATA
django_aiml-0.0.0.dist-info/RECORD
