Metadata-Version: 2.1
Name: django-aiml
Version: 0.0.0
Summary: Django AIML
Home-page: https://github.com/jeffmaxey/django-aiml
License: MIT
Author: Jeff A. Maxey
Author-email: jeffmaxey@comcast.net
Requires-Python: >=3.6.1,<4.0.0
Classifier: Development Status :: 3 - Alpha
Classifier: License :: OSI Approved :: MIT License
Classifier: Programming Language :: Python :: 3
Classifier: Programming Language :: Python :: 3.6
Classifier: Programming Language :: Python :: 3.7
Classifier: Programming Language :: Python :: 3.8
Classifier: Programming Language :: Python :: 3.9
Requires-Dist: click (>=8.0.1,<9.0.0)
Project-URL: Changelog, https://github.com/jeffmaxey/django-aiml/releases
Project-URL: Documentation, https://django-aiml.readthedocs.io
Project-URL: Repository, https://github.com/jeffmaxey/django-aiml
